{
  "project_info": {
    "project_number": "941975046224",
    "project_id": "remindertest-f0b80",
    "storage_bucket": "remindertest-f0b80.appspot.com"
  },
  "client": [
    {
      "client_info": {
        "mobilesdk_app_id": "1:941975046224:android:8fa96d61938d2ecdafe955",
        "android_client_info": {
          "package_name": "com.whatsapp"
        }
      },
      "oauth_client": [
        {
          "client_id": "941975046224-5nvjsb3261er3g6rnv9linpta81a91sv.apps.googleusercontent.com",
          "client_type": 3
        }
      ],
      "api_key": [
        {
          "current_key": "AIzaSyCSrLQpaBktjZTb6-IRgzkF2w8cNfmA58c"
        }
      ],
      "services": {
        "appinvite_service": {
          "other_platform_oauth_client": [
            {
              "client_id": "941975046224-5nvjsb3261er3g6rnv9linpta81a91sv.apps.googleusercontent.com",
              "client_type": 3
            }
          ]
        }
      }
    }
  ],
  "configuration_version": "1"
}